Metadata-Version: 2.1
Name: odoo8-addon-account-chart-update
Version: 8.0.1.2.0.99.dev51
Summary: Detect changes and update the Account Chart from a template
Home-page: http://odoo-community.org
Author: Zikzakmedia SL, Pexego, Serv. Tecnol. Avanzados - Pedro M. Baeza, ACSONE A/V, Odoo Community Association (OCA)
Author-email: support@odoo-community.org
License: AGPL-3
Platform: UNKNOWN
Classifier: Programming Language :: Python
Classifier: Framework :: Odoo
Classifier: Framework :: Odoo :: 8.0
Classifier: License :: OSI Approved :: GNU Affero General Public License v3
Requires-Python: ~=2.7
Requires-Dist: odoo (<9.0a,>=8.0a)
